[{"id":0,"time":1748514528,"name":"Anonymous","content":"hello"},{"id":1,"time":1748514540,"name":"pd","content":"ssds"},{"id":2,"time":1748515107,"name":"pd","content":"sdsd"},{"id":3,"time":1748515111,"name":"pd","content":"dsds"},{"id":4,"time":1748515497,"name":"kk","content":"Bol lodu"},{"id":5,"time":1748516038,"name":"Anonymous","content":"dsdsdsd"},{"id":6,"time":1748516047,"name":"Anonymous","content":"dsdsdsd"},{"id":7,"time":1748516072,"name":"Anonymous","content":"dsdsd"},{"id":8,"time":1748516094,"name":"kk","content":"le le grok le ..."},{"id":9,"time":1748516125,"name":"kk","content":"le le "},{"id":10,"time":1748516380,"name":"kk","content":"jat kar e ..."},{"id":11,"time":1748516404,"name":"pd","content":"haa"},{"id":12,"time":1748516489,"name":"kk","content":"su haaa jaldi joi mare"},{"id":13,"time":1748516500,"name":"kk","content":"jaldi joi mare"},{"id":14,"time":1748516524,"name":"pd","content":"sdsds"},{"id":15,"time":1748516550,"name":"kk","content":"vaah"},{"id":16,"time":1748516559,"name":"kk","content":"hve notification joi ..."},{"id":17,"time":1748516602,"name":"kk","content":"\ud83d\ude39\ud83d\udc6d\ud83d\ude30\ud83d\udc79\ud83d\udc6a\ud83d\ude30\ud83d\udc66\ud83d\udc73\ud83d\udc74\ud83d\udc70\ud83d\udc76\ud83d\udc70\ud83d\udc6c\ud83d\ude36\ud83d\udc6b\ud83d\ude4e\ud83d\udc71\ud83d\udc66\ud83d\udc62\ud83d\udc79\ud83d\ude4b\ud83d\udc56\ud83d\udc6b\ud83d\ude35\ud83d\udc70\ud83d\udc66\ud83d\udc73\ud83d\udc58\ud83d\ude41\ud83d\ude39\ud83d\udc76\ud83d\udc54\ud83d\ude44\ud83d\ude2b\ud83d\udc69\ud83d\udc57\ud83d\udc4f\ud83d\ude38\ud83d\ude33\ud83d\udc56\ud83d\ude43\ud83d\udc57\ud83d\udc70\ud83d\ude39\ud83d\ude35\ud83d\udc53\ud83d\udc4c\ud83d\udc78\ud83d\udc7a\ud83d\ude4b\ud83d\udc73\ud83d\ude48\ud83d\udc74\ud83d\udc73"},{"id":18,"time":1748516659,"name":"pd","content":"\ud83d\ude41"},{"id":19,"time":1748516662,"name":"pd","content":"sd"},{"id":20,"time":1748516701,"name":"pd","content":"hello"},{"id":21,"time":1748516711,"name":"kk","content":"\ud83d\ude2b\ud83d\ude47\ud83d\udc51\ud83d\ude45\ud83d\ude2b\ud83d\ude38\ud83d\udc66\ud83d\udc51\ud83d\udc68\ud83d\udc7a\ud83d\udc55\ud83d\ude49\ud83d\udc64\ud83d\udc6a\ud83d\udc73\ud83d\udc75\ud83d\ude39\ud83d\udc79\ud83d\ude41\ud83d\udc6d\ud83d\udc71\ud83d\ude43\ud83d\udc76\ud83d\udc65\ud83d\udc57\ud83d\udc72\ud83d\ude33\ud83d\udc4c\ud83d\udc62\ud83d\udc7a\ud83d\udc70\ud83d\udc71\ud83d\ude36\ud83d\udc5a\ud83d\udc58\ud83d\udc4f\ud83d\ude36\ud83d\ude34\ud83d\udc6a\ud83d\udc54\ud83d\udc76\ud83d\ude37\ud83d\udc7a\ud83d\udc57\ud83d\udc6c\ud83d\udc5a\ud83d\udc6c\ud83d\udc58\ud83d\udc61\ud83d\udc6b\ud83d\ude4e\ud83d\udc68\ud83d\ude32\ud83d\ude45"},{"id":22,"time":1748516749,"name":"kk","content":"hey lodu"},{"id":23,"time":1748516755,"name":"pd","content":"zhal lo"},{"id":24,"time":1748516790,"name":"pd","content":"dsds"},{"id":25,"time":1748517555,"name":"kk","content":"Hello"},{"id":26,"time":1748517564,"name":"kk","content":"lyo"},{"id":27,"time":1748517570,"name":"kk","content":"jaydha ne .."},{"id":28,"time":1748518094,"name":"kk","content":"jadhi ne joda jevu kayru .."},{"id":29,"time":1748518117,"name":"pd","content":"eh haa ho"},{"id":30,"time":1748518122,"name":"pd","content":"hmna thai ajse"},{"id":31,"time":1748518124,"name":"pd","content":"jase"},{"id":32,"time":1748518126,"name":"pd","content":"time lage "},{"id":33,"time":1748518167,"name":"pd","content":"sdsds"},{"id":34,"time":1748518768,"name":"pd","content":"hello"},{"id":35,"time":1748518787,"name":"pd","content":"hello"},{"id":36,"time":1748518940,"name":"pd","content":"hello testing"},{"id":37,"time":1748518953,"name":"kk","content":"helllo"},{"id":38,"time":1748518961,"name":"kk","content":"zhal lyo ..."},{"id":39,"time":1748519051,"name":"kamlesh","content":"kar le"},{"id":40,"time":1748519342,"name":"pd","content":"lora"},{"id":41,"time":1748519493,"name":"kamlesh","content":"vaaah"},{"id":42,"time":1748519500,"name":"pd","content":"123"},{"id":43,"time":1748519513,"name":"kamlesh","content":"122313"},{"id":44,"time":1748520527,"name":"pd","content":"dssds"},{"id":45,"time":1748520530,"name":"pd","content":"sdsd"}]